AUTHORS.rst
ChangeLog.rst
MANIFEST.in
README.rst
setup.py
negar_cli/__init__.py
negar_cli/negar_cli.py
negar_cli/version.py
negar_cli.egg-info/PKG-INFO
negar_cli.egg-info/SOURCES.txt
negar_cli.egg-info/dependency_links.txt
negar_cli.egg-info/entry_points.txt
negar_cli.egg-info/requires.txt
negar_cli.egg-info/top_level.txt