Metadata-Version: 2.1
Name: negar-cli
Version: 1.1
Summary: Negar Command Line Interface.
Home-page: https://github.com/Alir3z4/negar-cli
Author: Shahin Azad
Author-email: ishahinism@gmail.com
Maintainer: Javad Razavian, Alireza Savand
Maintainer-email: javadr@gmail.com, alireza.savand@gmail.com
License: GPLv3
Keywords: negar,cli,negar-cli,texteditor,persian
Platform: UNKNOWN
License-File: AUTHORS.rst
